pearhash
