Metadata-Version: 1.0
Name: pearhash
Version: 1.0.0
Summary: Pearson hashing algorithm
Home-page: https://github.com/ze-phyr-us/pearhash
Author: Vita Smid
Author-email: me@ze.phyr.us
License: MIT
Platform: UNKNOWN
